minumtium_fastapi/__init__.py
minumtium_fastapi/auth.py
minumtium_fastapi/deps.py
minumtium_fastapi/routes/__init__.py
minumtium_fastapi/routes/auth.py
minumtium_fastapi/routes/posts.py
minumtium_fastapi/routes/users.py
minumtium_fastapi-1.1.0.dist-info/LICENSE
minumtium_fastapi-1.1.0.dist-info/METADATA
minumtium_fastapi-1.1.0.dist-info/WHEEL
minumtium_fastapi-1.1.0.dist-info/top_level.txt
minumtium_fastapi-1.1.0.dist-info/RECORD
