Metadata-Version: 2.1
Name: minumtium-fastapi
Version: 1.1.0
Summary: A FastAPI application layer for the minumtium library.
Home-page: https://github.com/danodic-dev/minumtium-fastapi
Author: Danilo Guimaraes (danodic)
Author-email: danilo@danodic.dev
Project-URL: Bug Tracker, https://github.com/danodic-dev/minumtium-fastapi/issues
Classifier: Development Status :: 3 - Alpha
Classifier: Programming Language :: Python :: 3
Classifier: License :: OSI Approved :: Apache Software License
Classifier: Operating System :: OS Independent
Requires-Python: >=3.6
License-File: LICENSE
Requires-Dist: pydantic
Requires-Dist: fastapi
Requires-Dist: minumtium
Requires-Dist: minumtium-sqlite
Requires-Dist: minumtium-simple-jwt-auth
